sentry_custom_mailer/plugin.py
sentry_custom_mailer/__init__.py
sentry_custom_mailer-1.0.4.dist-info/METADATA
sentry_custom_mailer-1.0.4.dist-info/DESCRIPTION.rst
sentry_custom_mailer-1.0.4.dist-info/top_level.txt
sentry_custom_mailer-1.0.4.dist-info/entry_points.txt
sentry_custom_mailer-1.0.4.dist-info/metadata.json
sentry_custom_mailer-1.0.4.dist-info/WHEEL
sentry_custom_mailer-1.0.4.dist-info/RECORD
