Metadata-Version: 2.0
Name: sentry-custom-mailer
Version: 1.0.4
Summary: A sentry plugin to specify recipients of notification emails
Home-page: UNKNOWN
Author: Kieran Broekhoven
Author-email: kbroekhoven@clearpathrobotics.com
License: UNKNOWN
Platform: UNKNOWN
Requires-Dist: django
Requires-Dist: django-multi-email-field
Requires-Dist: sentry
